[
  {
    "id": "1776156924588",
    "name": "Sarah Connor",
    "email": "sarah.connor@cyberdyne.com",
    "department": "Security",
    "position": "Lead Guard",
    "employeeId": "EMP-002",
    "phone": "9876543210",
    "photo": "https://api.dicebear.com/7.x/avataaars/svg?seed=Sarah",
    "image": [],
    "registeredAt": "2026-04-14T09:00:00.000Z"
  },
  {
    "id": "1776156924589",
    "name": "James Smith",
    "email": "james.smith@company.com",
    "department": "Engineering",
    "position": "Software Engineer",
    "employeeId": "EMP-003",
    "phone": "9876512345",
    "photo": "https://api.dicebear.com/7.x/avataaars/svg?seed=James",
    "image": [],
    "registeredAt": "2026-04-14T09:05:00.000Z"
  },
  {
    "id": "1776156924590",
    "name": "Elena Rodriguez",
    "email": "elena.r@company.com",
    "department": "Design",
    "position": "UX Designer",
    "employeeId": "EMP-004",
    "phone": "9876598765",
    "photo": "https://api.dicebear.com/7.x/avataaars/svg?seed=Elena",
    "image": [],
    "registeredAt": "2026-04-14T09:10:00.000Z"
  },
  {
    "id": "1776156924591",
    "name": "Michael Chen",
    "email": "m.chen@company.com",
    "department": "Marketing",
    "position": "Manager",
    "employeeId": "EMP-005",
    "phone": "9876555555",
    "photo": "https://api.dicebear.com/7.x/avataaars/svg?seed=Michael",
    "image": [],
    "registeredAt": "2026-04-14T09:15:00.000Z"
  },
  {
    "id": "1776156924592",
    "name": "Aiswarya Roy",
    "email": "aiswarya.roy@company.com",
    "department": "Engineering",
    "position": "Frontend Dev",
    "employeeId": "EMP-006",
    "phone": "9876544444",
    "photo": "https://api.dicebear.com/7.x/avataaars/svg?seed=Aiswarya",
    "image": [],
    "registeredAt": "2026-04-14T09:20:00.000Z"
  },
  {
    "id": "1776156924593",
    "name": "David Miller",
    "email": "d.miller@company.com",
    "department": "Finance",
    "position": "Accountant",
    "employeeId": "EMP-007",
    "phone": "9876533333",
    "photo": "https://api.dicebear.com/7.x/avataaars/svg?seed=David",
    "image": [],
    "registeredAt": "2026-04-14T09:25:00.000Z"
  },
  {
    "id": "1776156924594",
    "name": "Sophia Brown",
    "email": "sophia.b@company.com",
    "department": "HR",
    "position": "HR Specialist",
    "employeeId": "EMP-008",
    "phone": "9876522222",
    "photo": "https://api.dicebear.com/7.x/avataaars/svg?seed=Sophia",
    "image": [],
    "registeredAt": "2026-04-14T09:30:00.000Z"
  },
  {
    "id": "1776156924595",
    "name": "Robert Wilson",
    "email": "r.wilson@company.com",
    "department": "Operations",
    "position": "Supervisor",
    "employeeId": "EMP-009",
    "phone": "9876511111",
    "photo": "https://api.dicebear.com/7.x/avataaars/svg?seed=Robert",
    "image": [],
    "registeredAt": "2026-04-14T09:35:00.000Z"
  },
  {
    "id": "1776156924596",
    "name": "Linda Zhang",
    "email": "linda.z@company.com",
    "department": "Quality Assurance",
    "position": "QA Engineer",
    "employeeId": "EMP-010",
    "phone": "9876500000",
    "photo": "https://api.dicebear.com/7.x/avataaars/svg?seed=Linda",
    "image": [],
    "registeredAt": "2026-04-14T09:40:00.000Z"
  },
  {
    "id": "1776156924597",
    "name": "Tom Anderson",
    "email": "neo@company.com",
    "department": "Engineering",
    "position": "Senior Developer",
    "employeeId": "EMP-011",
    "phone": "9876599999",
    "photo": "https://api.dicebear.com/7.x/avataaars/svg?seed=Tom",
    "image": [],
    "registeredAt": "2026-04-14T09:45:00.000Z"
  },
  {
    "id": "1776156924598",
    "name": "Monika Geller",
    "email": "monika.g@company.com",
    "department": "Food & Beverage",
    "position": "Head Chef",
    "employeeId": "EMP-012",
    "phone": "9876588888",
    "photo": "https://api.dicebear.com/7.x/avataaars/svg?seed=Monika",
    "image": [],
    "registeredAt": "2026-04-14T09:50:00.000Z"
  },
  {
    "id": "1776156924599",
    "name": "Chandler Bing",
    "email": "c.bing@company.com",
    "department": "Data Science",
    "position": "Statistical Analyst",
    "employeeId": "EMP-013",
    "phone": "9876577777",
    "photo": "https://api.dicebear.com/7.x/avataaars/svg?seed=Chandler",
    "image": [],
    "registeredAt": "2026-04-14T09:55:00.000Z"
  },
  {
    "id": "1776156924600",
    "name": "Rachel Green",
    "email": "rachel.styling@company.com",
    "department": "Marketing",
    "position": "Senior Stylist",
    "employeeId": "EMP-014",
    "phone": "9876566666",
    "photo": "https://api.dicebear.com/7.x/avataaars/svg?seed=Rachel",
    "image": [],
    "registeredAt": "2026-04-14T10:00:00.000Z"
  },
  {
    "id": "1776156924601",
    "name": "Joey Tribbiani",
    "email": "joey@company.com",
    "department": "Entertainment",
    "position": "Brand Ambassador",
    "employeeId": "EMP-015",
    "phone": "9876544441",
    "photo": "https://api.dicebear.com/7.x/avataaars/svg?seed=Joey",
    "image": [],
    "registeredAt": "2026-04-14T10:05:00.000Z"
  },
  {
    "id": "1776156924602",
    "name": "Ross Geller",
    "email": "dino.man@company.com",
    "department": "Archives",
    "position": "Senior Curator",
    "employeeId": "EMP-016",
    "phone": "9876544442",
    "photo": "https://api.dicebear.com/7.x/avataaars/svg?seed=Ross",
    "image": [],
    "registeredAt": "2026-04-14T10:10:00.000Z"
  },
  {
    "id": "1776156924603",
    "name": "Phoebe Buffay",
    "email": "phoebe.songs@company.com",
    "department": "Wellness",
    "position": "Masseuse",
    "employeeId": "EMP-017",
    "phone": "9876544443",
    "photo": "https://api.dicebear.com/7.x/avataaars/svg?seed=Phoebe",
    "image": [],
    "registeredAt": "2026-04-14T10:15:00.000Z"
  },
  {
    "id": "1776156924604",
    "name": "Bruce Wayne",
    "email": "bruce@wayne.com",
    "department": "Executive",
    "position": "Chairman",
    "employeeId": "EMP-018",
    "phone": "9876544444",
    "photo": "https://api.dicebear.com/7.x/avataaars/svg?seed=Bruce",
    "image": [],
    "registeredAt": "2026-04-14T10:20:00.000Z"
  },
  {
    "id": "1776156924605",
    "name": "Clark Kent",
    "email": "clark@planet.com",
    "department": "Public Relations",
    "position": "Reporter",
    "employeeId": "EMP-019",
    "phone": "9876544445",
    "photo": "https://api.dicebear.com/7.x/avataaars/svg?seed=Clark",
    "image": [],
    "registeredAt": "2026-04-14T10:25:00.000Z"
  },
  {
    "id": "1776156924606",
    "name": "Diana Prince",
    "email": "diana@themyscira.com",
    "department": "Security",
    "position": "Field Agent",
    "employeeId": "EMP-020",
    "phone": "9876544446",
    "photo": "https://api.dicebear.com/7.x/avataaars/svg?seed=Diana",
    "image": [],
    "registeredAt": "2026-04-14T10:30:00.000Z"
  },
  {
    "id": "1776156924607",
    "name": "Peter Parker",
    "email": "p.parker@dailybugle.com",
    "department": "Photography",
    "position": "Photographer",
    "employeeId": "EMP-021",
    "phone": "9876544447",
    "photo": "https://api.dicebear.com/7.x/avataaars/svg?seed=Peter",
    "image": [],
    "registeredAt": "2026-04-14T10:35:00.000Z"
  },
  {
    "id": "1776156924608",
    "name": "Tony Stark",
    "email": "tony@stark.com",
    "department": "Engineering",
    "position": "CTO",
    "employeeId": "EMP-022",
    "phone": "9876544448",
    "photo": "https://api.dicebear.com/7.x/avataaars/svg?seed=Tony",
    "image": [],
    "registeredAt": "2026-04-14T10:40:00.000Z"
  },
  {
    "id": "1776156924609",
    "name": "Steve Rogers",
    "email": "cap@america.com",
    "department": "Strategy",
    "position": "Captain",
    "employeeId": "EMP-023",
    "phone": "9876544449",
    "photo": "https://api.dicebear.com/7.x/avataaars/svg?seed=Steve",
    "image": [],
    "registeredAt": "2026-04-14T10:45:00.000Z"
  },
  {
    "id": "1776156924610",
    "name": "Natasha Romanoff",
    "email": "natasha@shield.com",
    "department": "Operations",
    "position": "Specialist",
    "employeeId": "EMP-024",
    "phone": "9876544450",
    "photo": "https://api.dicebear.com/7.x/avataaars/svg?seed=Natasha",
    "image": [],
    "registeredAt": "2026-04-14T10:50:00.000Z"
  },
  {
    "id": "1776156924611",
    "name": "Wanda Maximoff",
    "email": "wanda@westview.com",
    "department": "Research",
    "position": "Researcher",
    "employeeId": "EMP-025",
    "phone": "9876544451",
    "photo": "https://api.dicebear.com/7.x/avataaars/svg?seed=Wanda",
    "image": [],
    "registeredAt": "2026-04-14T10:55:00.000Z"
  },
  {
    "id": "1776156924612",
    "name": "Loki Laufeyson",
    "email": "loki@asgard.com",
    "department": "Support",
    "position": "Agent of Chaos",
    "employeeId": "EMP-026",
    "phone": "9876544452",
    "photo": "https://api.dicebear.com/7.x/avataaars/svg?seed=Loki",
    "image": [],
    "registeredAt": "2026-04-14T11:00:00.000Z"
  },
  {
    "id": "1776156924613",
    "name": "Thor Odinson",
    "email": "thor@thunder.com",
    "department": "Security",
    "position": "Guardian",
    "employeeId": "EMP-027",
    "phone": "9876544453",
    "photo": "https://api.dicebear.com/7.x/avataaars/svg?seed=Thor",
    "image": [],
    "registeredAt": "2026-04-14T11:05:00.000Z"
  },
  {
    "id": "1776156924614",
    "name": "Barry Allen",
    "email": "barry@flash.com",
    "department": "Logistics",
    "position": "Speed Runner",
    "employeeId": "EMP-028",
    "phone": "9876544454",
    "photo": "https://api.dicebear.com/7.x/avataaars/svg?seed=Barry",
    "image": [],
    "registeredAt": "2026-04-14T11:10:00.000Z"
  },
  {
    "id": "1776156924615",
    "name": "Arthur Curry",
    "email": "aquaman@ocean.com",
    "department": "Facilities",
    "position": "Warden",
    "employeeId": "EMP-029",
    "phone": "9876544455",
    "photo": "https://api.dicebear.com/7.x/avataaars/svg?seed=Arthur",
    "image": [],
    "registeredAt": "2026-04-14T11:15:00.000Z"
  },
  {
    "id": "1776156924616",
    "name": "Hal Jordan",
    "email": "hal@lantern.com",
    "department": "Aviation",
    "position": "Pilot",
    "employeeId": "EMP-030",
    "phone": "9876544456",
    "photo": "https://api.dicebear.com/7.x/avataaars/svg?seed=Hal",
    "image": [],
    "registeredAt": "2026-04-14T11:20:00.000Z"
  },
  {
    "id": "1776156924617",
    "name": "Victor Stone",
    "email": "victor@star.com",
    "department": "IT Support",
    "position": "Network Lead",
    "employeeId": "EMP-031",
    "phone": "9876544457",
    "photo": "https://api.dicebear.com/7.x/avataaars/svg?seed=Victor",
    "image": [],
    "registeredAt": "2026-04-14T11:25:00.000Z"
  }
]